celest/__init__.py
celest/angle_strings.py
celest/constants.py
celest/file_save.py
celest/satellite.py
celest/time.py
celest/coordinates/__init__.py
celest/coordinates/astronomical_quantities.py
celest/coordinates/coordinate.py
celest/coordinates/ground_location.py
celest/coordinates/nutation_precession_matrices.py
celest/coordinates/transforms.py
celest/coordinates/frames/__init__.py
celest/coordinates/frames/attitude.py
celest/coordinates/frames/azel.py
celest/coordinates/frames/base_positions.py
celest/coordinates/frames/gcrs.py
celest/coordinates/frames/itrs.py
celest/coordinates/frames/lvlh.py
celest/coordinates/frames/wgs84.py
celest/data/de421.bsp
celest/encounter/__init__.py
celest/encounter/window_generator.py
celest/encounter/window_handling.py
celest/schedule/__init__.py
celest/schedule/alns.py
celest/schedule/insertion_operators.py
celest/schedule/removal_operators.py
celest/schedule/request_handler.py
celest/schedule/scheduler.py
celest/schedule/scheduling_utils.py
celest/units/__init__.py
celest/units/core.py
celest/units/display.py
celest/units/quantity.py
celest/units/unit_initialization.py
celest/units/utils.py
celest-1.0.0.dist-info/LICENSE.txt
celest-1.0.0.dist-info/METADATA
celest-1.0.0.dist-info/WHEEL
celest-1.0.0.dist-info/top_level.txt
celest-1.0.0.dist-info/RECORD
