Metadata-Version: 2.1
Name: celest
Version: 1.0.0
Summary: Satellite dynamics and mission planning library.
Home-page: https://github.com/JaiWillems/Celest
Download-URL: https://pypi.org/project/celest/
Author: Jai Willems et al.
Author-email: jai52h@hotmail.com
License: BSD
Project-URL: Bug Tracker, https://github.com/JaiWillems/celest/issues
Project-URL: Documentation, https://celest.readthedocs.io/en/latest/
Project-URL: Source Code, https://github.com/JaiWillems/celest
Classifier: Development Status :: 5 - Production/Stable
Classifier: Intended Audience :: Science/Research
Classifier: Programming Language :: Python :: 3.8
Classifier: Programming Language :: Python :: 3.9
Classifier: Programming Language :: Python :: 3.10
Classifier: License :: OSI Approved :: BSD License
Classifier: Operating System :: OS Independent
Classifier: Topic :: Scientific/Engineering
Requires-Python: >=3.8
License-File: LICENSE.txt
Requires-Dist: jplephem
Requires-Dist: julian
Requires-Dist: numpy
